[{"robot_id": "aqua-robot-001", "timestamp": "2025-11-06T05:39:00.737809", "mission": 1, "state": "NAVIGATING", "sensor_readings": {"pH": 7.0, "turbidity": 2.92, "temperature": 29.35, "TDS": 547.03}, "water_quality": {"score": 58.5, "status": "Fair", "warnings": ["TDS level is high (>500 ppm)"]}}, {"robot_id": "aqua-robot-001", "timestamp": "2025-11-06T05:39:01.741331", "mission": 1, "state": "NAVIGATING", "sensor_readings": {"pH": 9.41, "turbidity": 8.01, "temperature": 23.11, "TDS": 322.14}, "water_quality": {"score": 64.02, "status": "Fair", "warnings": ["pH level is out of safe range (6.5-8.5)", "Turbidity is high (>5 NTU)"]}}, {"robot_id": "aqua-robot-001", "timestamp": "2025-11-06T05:39:02.744852", "mission": 1, "state": "NAVIGATING", "sensor_readings": {"pH": 8.21, "turbidity": 2.66, "temperature": 31.43, "TDS": 706.14}, "water_quality": {"score": 55.84, "status": "Fair", "warnings": ["Temperature is too high (>30\u00b0C)", "TDS level is high (>500 ppm)"]}}, {"robot_id": "aqua-robot-001", "timestamp": "2025-11-06T05:39:03.748402", "mission": 1, "state": "NAVIGATING", "sensor_readings": {"pH": 5.89, "turbidity": 2.57, "temperature": 19.67, "TDS": 102.61}, "water_quality": {"score": 79.34, "status": "Good", "warnings": ["pH level is out of safe range (6.5-8.5)"]}}, {"robot_id": "aqua-robot-001", "timestamp": "2025-11-06T05:39:04.752114", "mission": 1, "state": "NAVIGATING", "sensor_readings": {"pH": 7.56, "turbidity": 0.49, "temperature": 21.63, "TDS": 503.11}, "water_quality": {"score": 77.18, "status": "Good", "warnings": ["TDS level is high (>500 ppm)"]}}, {"robot_id": "aqua-robot-001", "timestamp": "2025-11-06T05:39:05.755637", "mission": 1, "state": "NAVIGATING", "sensor_readings": {"pH": 7.78, "turbidity": 4.54, "temperature": 28.22, "TDS": 182.69}, "water_quality": {"score": 66.02, "status": "Fair", "warnings": []}}, {"robot_id": "aqua-robot-001", "timestamp": "2025-11-06T05:39:06.759180", "mission": 1, "state": "NAVIGATING", "sensor_readings": {"pH": 5.72, "turbidity": 0.17, "temperature": 19.76, "TDS": 743.39}, "water_quality": {"score": 64.6, "status": "Fair", "warnings": ["pH level is out of safe range (6.5-8.5)", "TDS level is high (>500 ppm)"]}}, {"robot_id": "aqua-robot-001", "timestamp": "2025-11-06T05:39:07.763247", "mission": 1, "state": "NAVIGATING", "sensor_readings": {"pH": 8.31, "turbidity": 7.43, "temperature": 28.56, "TDS": 537.03}, "water_quality": {"score": 46.6, "status": "Poor", "warnings": ["Turbidity is high (>5 NTU)", "TDS level is high (>500 ppm)"]}}, {"robot_id": "aqua-robot-001", "timestamp": "2025-11-06T05:39:08.766818", "mission": 1, "state": "NAVIGATING", "sensor_readings": {"pH": 8.36, "turbidity": 8.49, "temperature": 26.77, "TDS": 312.0}, "water_quality": {"score": 63.28, "status": "Fair", "warnings": ["Turbidity is high (>5 NTU)"]}}, {"robot_id": "aqua-robot-001", "timestamp": "2025-11-06T05:39:11.770839", "mission": 1, "state": "NAVIGATING", "sensor_readings": {"pH": 7.66, "turbidity": 7.33, "temperature": 29.55, "TDS": 946.39}, "water_quality": {"score": 39.3, "status": "Poor", "warnings": ["Turbidity is high (>5 NTU)", "TDS level is high (>500 ppm)"]}}, {"robot_id": "aqua-robot-001", "timestamp": "2025-11-06T05:39:12.774781", "mission": 1, "state": "NAVIGATING", "sensor_readings": {"pH": 7.45, "turbidity": 3.03, "temperature": 20.2, "TDS": 844.05}, "water_quality": {"score": 62.7, "status": "Fair", "warnings": ["TDS level is high (>500 ppm)"]}}, {"robot_id": "aqua-robot-001", "timestamp": "2025-11-06T05:39:13.778457", "mission": 1, "state": "NAVIGATING", "sensor_readings": {"pH": 7.05, "turbidity": 3.83, "temperature": 20.17, "TDS": 116.76}, "water_quality": {"score": 74.0, "status": "Good", "warnings": []}}, {"robot_id": "aqua-robot-001", "timestamp": "2025-11-06T05:39:14.782392", "mission": 1, "state": "NAVIGATING", "sensor_readings": {"pH": 7.63, "turbidity": 7.97, "temperature": 27.73, "TDS": 820.29}, "water_quality": {"score": 41.9, "status": "Poor", "warnings": ["Turbidity is high (>5 NTU)", "TDS level is high (>500 ppm)"]}}, {"robot_id": "aqua-robot-001", "timestamp": "2025-11-06T05:39:15.786326", "mission": 1, "state": "NAVIGATING", "sensor_readings": {"pH": 8.77, "turbidity": 0.66, "temperature": 16.72, "TDS": 414.18}, "water_quality": {"score": 84.52, "status": "Good", "warnings": ["pH level is out of safe range (6.5-8.5)"]}}, {"robot_id": "aqua-robot-001", "timestamp": "2025-11-06T05:39:16.790073", "mission": 1, "state": "NAVIGATING", "sensor_readings": {"pH": 7.73, "turbidity": 5.44, "temperature": 26.11, "TDS": 346.74}, "water_quality": {"score": 67.42, "status": "Fair", "warnings": ["Turbidity is high (>5 NTU)"]}}, {"robot_id": "aqua-robot-001", "timestamp": "2025-11-06T05:39:17.794464", "mission": 1, "state": "NAVIGATING", "sensor_readings": {"pH": 7.99, "turbidity": 1.28, "temperature": 21.31, "TDS": 678.59}, "water_quality": {"score": 74.2, "status": "Good", "warnings": ["TDS level is high (>500 ppm)"]}}, {"robot_id": "aqua-robot-001", "timestamp": "2025-11-06T05:39:18.798422", "mission": 1, "state": "NAVIGATING", "sensor_readings": {"pH": 6.6, "turbidity": 1.01, "temperature": 21.4, "TDS": 452.54}, "water_quality": {"score": 76.32, "status": "Good", "warnings": []}}, {"robot_id": "aqua-robot-001", "timestamp": "2025-11-06T05:39:20.802325", "mission": 1, "state": "NAVIGATING", "sensor_readings": {"pH": 9.34, "turbidity": 8.06, "temperature": 16.09, "TDS": 83.85}, "water_quality": {"score": 68.12, "status": "Fair", "warnings": ["pH level is out of safe range (6.5-8.5)", "Turbidity is high (>5 NTU)"]}}, {"robot_id": "aqua-robot-001", "timestamp": "2025-11-06T05:39:21.806551", "mission": 1, "state": "NAVIGATING", "sensor_readings": {"pH": 6.84, "turbidity": 0.13, "temperature": 17.66, "TDS": 786.81}, "water_quality": {"score": 71.42, "status": "Good", "warnings": ["TDS level is high (>500 ppm)"]}}, {"robot_id": "aqua-robot-001", "timestamp": "2025-11-06T05:39:22.811499", "mission": 1, "state": "NAVIGATING", "sensor_readings": {"pH": 8.54, "turbidity": 1.96, "temperature": 23.22, "TDS": 713.11}, "water_quality": {"score": 68.34, "status": "Fair", "warnings": ["pH level is out of safe range (6.5-8.5)", "TDS level is high (>500 ppm)"]}}, {"robot_id": "aqua-robot-001", "timestamp": "2025-11-06T05:39:23.815586", "mission": 1, "state": "NAVIGATING", "sensor_readings": {"pH": 7.36, "turbidity": 6.66, "temperature": 23.34, "TDS": 912.52}, "water_quality": {"score": 49.66, "status": "Poor", "warnings": ["Turbidity is high (>5 NTU)", "TDS level is high (>500 ppm)"]}}, {"robot_id": "aqua-robot-001", "timestamp": "2025-11-06T05:39:25.819863", "mission": 1, "state": "NAVIGATING", "sensor_readings": {"pH": 7.07, "turbidity": 1.24, "temperature": 16.54, "TDS": 416.63}, "water_quality": {"score": 83.14, "status": "Good", "warnings": []}}, {"robot_id": "aqua-robot-001", "timestamp": "2025-11-06T05:39:26.823798", "mission": 1, "state": "NAVIGATING", "sensor_readings": {"pH": 9.0, "turbidity": 0.79, "temperature": 24.56, "TDS": 361.66}, "water_quality": {"score": 87.82, "status": "Good", "warnings": ["pH level is out of safe range (6.5-8.5)"]}}, {"robot_id": "aqua-robot-001", "timestamp": "2025-11-06T05:39:27.828437", "mission": 1, "state": "NAVIGATING", "sensor_readings": {"pH": 7.87, "turbidity": 0.49, "temperature": 23.12, "TDS": 116.32}, "water_quality": {"score": 93.46, "status": "Excellent", "warnings": []}}, {"robot_id": "aqua-robot-001", "timestamp": "2025-11-06T05:39:28.832581", "mission": 1, "state": "NAVIGATING", "sensor_readings": {"pH": 5.53, "turbidity": 7.35, "temperature": 25.24, "TDS": 572.2}, "water_quality": {"score": 47.3, "status": "Poor", "warnings": ["pH level is out of safe range (6.5-8.5)", "Turbidity is high (>5 NTU)", "TDS level is high (>500 ppm)"]}}, {"robot_id": "aqua-robot-001", "timestamp": "2025-11-06T05:39:29.836727", "mission": 1, "state": "NAVIGATING", "sensor_readings": {"pH": 6.62, "turbidity": 6.41, "temperature": 28.37, "TDS": 123.08}, "water_quality": {"score": 57.66, "status": "Fair", "warnings": ["Turbidity is high (>5 NTU)"]}}, {"robot_id": "aqua-robot-001", "timestamp": "2025-11-06T05:48:00.820079", "mission": 1, "state": "NAVIGATING", "sensor_readings": {"pH": 7.65, "turbidity": 3.04, "temperature": 29.04, "TDS": 121.17}, "water_quality": {"score": 71.92, "status": "Good", "warnings": []}}, {"robot_id": "aqua-robot-001", "timestamp": "2025-11-06T05:48:01.824318", "mission": 1, "state": "NAVIGATING", "sensor_readings": {"pH": 6.29, "turbidity": 2.22, "temperature": 19.17, "TDS": 711.36}, "water_quality": {"score": 60.68, "status": "Fair", "warnings": ["pH level is out of safe range (6.5-8.5)", "TDS level is high (>500 ppm)"]}}, {"robot_id": "aqua-robot-001", "timestamp": "2025-11-06T05:48:02.828611", "mission": 1, "state": "NAVIGATING", "sensor_readings": {"pH": 7.79, "turbidity": 8.59, "temperature": 23.24, "TDS": 855.9}, "water_quality": {"score": 48.96, "status": "Poor", "warnings": ["Turbidity is high (>5 NTU)", "TDS level is high (>500 ppm)"]}}, {"robot_id": "aqua-robot-001", "timestamp": "2025-11-06T05:48:03.832763", "mission": 1, "state": "NAVIGATING", "sensor_readings": {"pH": 9.37, "turbidity": 1.48, "temperature": 16.88, "TDS": 359.49}, "water_quality": {"score": 88.96, "status": "Good", "warnings": ["pH level is out of safe range (6.5-8.5)"]}}, {"robot_id": "aqua-robot-001", "timestamp": "2025-11-06T05:48:04.838468", "mission": 1, "state": "NAVIGATING", "sensor_readings": {"pH": 6.98, "turbidity": 9.8, "temperature": 31.7, "TDS": 434.11}, "water_quality": {"score": 48.2, "status": "Poor", "warnings": ["Turbidity is high (>5 NTU)", "Temperature is too high (>30\u00b0C)"]}}, {"robot_id": "aqua-robot-001", "timestamp": "2025-11-06T05:48:05.842753", "mission": 1, "state": "NAVIGATING", "sensor_readings": {"pH": 6.77, "turbidity": 1.91, "temperature": 24.88, "TDS": 926.78}, "water_quality": {"score": 66.78, "status": "Fair", "warnings": ["TDS level is high (>500 ppm)"]}}, {"robot_id": "aqua-robot-001", "timestamp": "2025-11-06T05:48:06.849516", "mission": 1, "state": "NAVIGATING", "sensor_readings": {"pH": 8.52, "turbidity": 8.73, "temperature": 21.55, "TDS": 382.5}, "water_quality": {"score": 60.54, "status": "Fair", "warnings": ["pH level is out of safe range (6.5-8.5)", "Turbidity is high (>5 NTU)"]}}, {"robot_id": "aqua-robot-001", "timestamp": "2025-11-06T05:48:07.860684", "mission": 1, "state": "NAVIGATING", "sensor_readings": {"pH": 7.63, "turbidity": 1.39, "temperature": 18.24, "TDS": 178.27}, "water_quality": {"score": 93.28, "status": "Excellent", "warnings": []}}, {"robot_id": "aqua-robot-001", "timestamp": "2025-11-06T05:48:08.866172", "mission": 1, "state": "NAVIGATING", "sensor_readings": {"pH": 6.68, "turbidity": 9.5, "temperature": 18.19, "TDS": 943.19}, "water_quality": {"score": 45.5, "status": "Poor", "warnings": ["Turbidity is high (>5 NTU)", "TDS level is high (>500 ppm)"]}}, {"robot_id": "aqua-robot-001", "timestamp": "2025-11-06T05:48:09.870902", "mission": 1, "state": "NAVIGATING", "sensor_readings": {"pH": 6.46, "turbidity": 3.64, "temperature": 22.86, "TDS": 569.6}, "water_quality": {"score": 57.4, "status": "Fair", "warnings": ["pH level is out of safe range (6.5-8.5)", "TDS level is high (>500 ppm)"]}}, {"robot_id": "aqua-robot-001", "timestamp": "2025-11-06T05:48:10.875416", "mission": 1, "state": "NAVIGATING", "sensor_readings": {"pH": 7.55, "turbidity": 3.55, "temperature": 19.9, "TDS": 126.84}, "water_quality": {"score": 77.74, "status": "Good", "warnings": []}}, {"robot_id": "aqua-robot-001", "timestamp": "2025-11-06T05:48:11.879769", "mission": 1, "state": "NAVIGATING", "sensor_readings": {"pH": 5.8, "turbidity": 5.16, "temperature": 26.33, "TDS": 246.01}, "water_quality": {"score": 67.06, "status": "Fair", "warnings": ["pH level is out of safe range (6.5-8.5)", "Turbidity is high (>5 NTU)"]}}, {"robot_id": "aqua-robot-001", "timestamp": "2025-11-06T05:48:12.884224", "mission": 1, "state": "NAVIGATING", "sensor_readings": {"pH": 7.33, "turbidity": 4.77, "temperature": 31.26, "TDS": 992.38}, "water_quality": {"score": 44.6, "status": "Poor", "warnings": ["Temperature is too high (>30\u00b0C)", "TDS level is high (>500 ppm)"]}}, {"robot_id": "aqua-robot-001", "timestamp": "2025-11-06T05:48:13.888513", "mission": 1, "state": "NAVIGATING", "sensor_readings": {"pH": 6.2, "turbidity": 9.65, "temperature": 26.21, "TDS": 942.01}, "water_quality": {"score": 43.24, "status": "Poor", "warnings": ["pH level is out of safe range (6.5-8.5)", "Turbidity is high (>5 NTU)", "TDS level is high (>500 ppm)"]}}, {"robot_id": "aqua-robot-001", "timestamp": "2025-11-06T05:48:14.893319", "mission": 1, "state": "NAVIGATING", "sensor_readings": {"pH": 8.83, "turbidity": 5.91, "temperature": 19.16, "TDS": 402.55}, "water_quality": {"score": 61.58, "status": "Fair", "warnings": ["pH level is out of safe range (6.5-8.5)", "Turbidity is high (>5 NTU)"]}}, {"robot_id": "aqua-robot-001", "timestamp": "2025-11-06T05:48:15.897714", "mission": 1, "state": "NAVIGATING", "sensor_readings": {"pH": 7.58, "turbidity": 4.09, "temperature": 24.93, "TDS": 499.89}, "water_quality": {"score": 60.3, "status": "Fair", "warnings": []}}, {"robot_id": "aqua-robot-001", "timestamp": "2025-11-06T05:48:16.902002", "mission": 1, "state": "NAVIGATING", "sensor_readings": {"pH": 8.59, "turbidity": 8.01, "temperature": 23.5, "TDS": 336.57}, "water_quality": {"score": 63.24, "status": "Fair", "warnings": ["pH level is out of safe range (6.5-8.5)", "Turbidity is high (>5 NTU)"]}}, {"robot_id": "aqua-robot-001", "timestamp": "2025-11-06T05:48:17.906449", "mission": 1, "state": "NAVIGATING", "sensor_readings": {"pH": 8.64, "turbidity": 9.32, "temperature": 21.34, "TDS": 88.59}, "water_quality": {"score": 68.12, "status": "Fair", "warnings": ["pH level is out of safe range (6.5-8.5)", "Turbidity is high (>5 NTU)"]}}, {"robot_id": "aqua-robot-001", "timestamp": "2025-11-06T05:48:18.910789", "mission": 1, "state": "NAVIGATING", "sensor_readings": {"pH": 7.02, "turbidity": 7.67, "temperature": 25.43, "TDS": 593.91}, "water_quality": {"score": 52.1, "status": "Fair", "warnings": ["Turbidity is high (>5 NTU)", "TDS level is high (>500 ppm)"]}}, {"robot_id": "aqua-robot-001", "timestamp": "2025-11-06T05:48:19.915246", "mission": 1, "state": "NAVIGATING", "sensor_readings": {"pH": 6.88, "turbidity": 4.92, "temperature": 31.2, "TDS": 578.96}, "water_quality": {"score": 48.7, "status": "Poor", "warnings": ["Temperature is too high (>30\u00b0C)", "TDS level is high (>500 ppm)"]}}, {"robot_id": "aqua-robot-001", "timestamp": "2025-11-06T05:48:20.919801", "mission": 1, "state": "NAVIGATING", "sensor_readings": {"pH": 7.79, "turbidity": 3.68, "temperature": 23.49, "TDS": 60.46}, "water_quality": {"score": 77.38, "status": "Good", "warnings": []}}, {"robot_id": "aqua-robot-001", "timestamp": "2025-11-06T05:48:21.924390", "mission": 1, "state": "NAVIGATING", "sensor_readings": {"pH": 5.61, "turbidity": 6.44, "temperature": 30.41, "TDS": 902.25}, "water_quality": {"score": 34.7, "status": "Poor", "warnings": ["pH level is out of safe range (6.5-8.5)", "Turbidity is high (>5 NTU)", "Temperature is too high (>30\u00b0C)", "TDS level is high (>500 ppm)"]}}, {"robot_id": "aqua-robot-001", "timestamp": "2025-11-06T05:48:22.928944", "mission": 1, "state": "NAVIGATING", "sensor_readings": {"pH": 7.63, "turbidity": 8.46, "temperature": 22.99, "TDS": 745.02}, "water_quality": {"score": 48.96, "status": "Poor", "warnings": ["Turbidity is high (>5 NTU)", "TDS level is high (>500 ppm)"]}}, {"robot_id": "aqua-robot-001", "timestamp": "2025-11-06T05:48:23.933643", "mission": 1, "state": "NAVIGATING", "sensor_readings": {"pH": 6.81, "turbidity": 4.4, "temperature": 18.6, "TDS": 630.8}, "water_quality": {"score": 56.4, "status": "Fair", "warnings": ["TDS level is high (>500 ppm)"]}}, {"robot_id": "aqua-robot-001", "timestamp": "2025-11-06T05:48:24.938492", "mission": 1, "state": "NAVIGATING", "sensor_readings": {"pH": 9.22, "turbidity": 3.38, "temperature": 31.52, "TDS": 488.51}, "water_quality": {"score": 57.1, "status": "Fair", "warnings": ["pH level is out of safe range (6.5-8.5)", "Temperature is too high (>30\u00b0C)"]}}, {"robot_id": "aqua-robot-001", "timestamp": "2025-11-06T05:48:25.943088", "mission": 1, "state": "NAVIGATING", "sensor_readings": {"pH": 8.62, "turbidity": 2.52, "temperature": 21.73, "TDS": 536.63}, "water_quality": {"score": 69.76, "status": "Fair", "warnings": ["pH level is out of safe range (6.5-8.5)", "TDS level is high (>500 ppm)"]}}, {"robot_id": "aqua-robot-001", "timestamp": "2025-11-06T05:48:26.947989", "mission": 1, "state": "NAVIGATING", "sensor_readings": {"pH": 6.11, "turbidity": 6.46, "temperature": 15.14, "TDS": 151.01}, "water_quality": {"score": 64.04, "status": "Fair", "warnings": ["pH level is out of safe range (6.5-8.5)", "Turbidity is high (>5 NTU)"]}}, {"robot_id": "aqua-robot-001", "timestamp": "2025-11-06T05:48:27.952668", "mission": 1, "state": "NAVIGATING", "sensor_readings": {"pH": 7.7, "turbidity": 9.37, "temperature": 25.82, "TDS": 481.51}, "water_quality": {"score": 52.8, "status": "Fair", "warnings": ["Turbidity is high (>5 NTU)"]}}, {"robot_id": "aqua-robot-001", "timestamp": "2025-11-06T05:48:28.957297", "mission": 1, "state": "NAVIGATING", "sensor_readings": {"pH": 5.87, "turbidity": 1.11, "temperature": 15.88, "TDS": 698.14}, "water_quality": {"score": 66.6, "status": "Fair", "warnings": ["pH level is out of safe range (6.5-8.5)", "TDS level is high (>500 ppm)"]}}, {"robot_id": "aqua-robot-001", "timestamp": "2025-11-06T05:48:29.962097", "mission": 1, "state": "NAVIGATING", "sensor_readings": {"pH": 8.46, "turbidity": 3.63, "temperature": 30.89, "TDS": 889.71}, "water_quality": {"score": 50.16, "status": "Fair", "warnings": ["Temperature is too high (>30\u00b0C)", "TDS level is high (>500 ppm)"]}}, {"robot_id": "aqua-robot-001", "timestamp": "2025-11-06T05:49:28.424538", "mission": 1, "state": "NAVIGATING", "sensor_readings": {"pH": 9.29, "turbidity": 3.52, "temperature": 26.83, "TDS": 413.5}, "water_quality": {"score": 67.48, "status": "Fair", "warnings": ["pH level is out of safe range (6.5-8.5)"]}}, {"robot_id": "aqua-robot-001", "timestamp": "2025-11-06T05:49:29.429273", "mission": 1, "state": "NAVIGATING", "sensor_readings": {"pH": 5.81, "turbidity": 3.66, "temperature": 28.28, "TDS": 963.05}, "water_quality": {"score": 46.3, "status": "Poor", "warnings": ["pH level is out of safe range (6.5-8.5)", "TDS level is high (>500 ppm)"]}}, {"robot_id": "aqua-robot-001", "timestamp": "2025-11-06T05:49:30.434037", "mission": 1, "state": "NAVIGATING", "sensor_readings": {"pH": 8.98, "turbidity": 9.6, "temperature": 21.16, "TDS": 316.42}, "water_quality": {"score": 64.38, "status": "Fair", "warnings": ["pH level is out of safe range (6.5-8.5)", "Turbidity is high (>5 NTU)"]}}, {"robot_id": "aqua-robot-001", "timestamp": "2025-11-06T05:49:31.439594", "mission": 1, "state": "NAVIGATING", "sensor_readings": {"pH": 7.51, "turbidity": 2.45, "temperature": 24.51, "TDS": 822.42}, "water_quality": {"score": 67.42, "status": "Fair", "warnings": ["TDS level is high (>500 ppm)"]}}, {"robot_id": "aqua-robot-001", "timestamp": "2025-11-06T05:49:32.444361", "mission": 1, "state": "NAVIGATING", "sensor_readings": {"pH": 7.24, "turbidity": 8.69, "temperature": 27.87, "TDS": 658.76}, "water_quality": {"score": 44.6, "status": "Poor", "warnings": ["Turbidity is high (>5 NTU)", "TDS level is high (>500 ppm)"]}}, {"robot_id": "aqua-robot-001", "timestamp": "2025-11-06T05:49:33.449385", "mission": 1, "state": "NAVIGATING", "sensor_readings": {"pH": 6.04, "turbidity": 1.29, "temperature": 34.84, "TDS": 154.38}, "water_quality": {"score": 73.18, "status": "Good", "warnings": ["pH level is out of safe range (6.5-8.5)", "Temperature is too high (>30\u00b0C)"]}}, {"robot_id": "aqua-robot-001", "timestamp": "2025-11-06T05:49:34.454426", "mission": 1, "state": "NAVIGATING", "sensor_readings": {"pH": 8.66, "turbidity": 9.54, "temperature": 26.22, "TDS": 56.37}, "water_quality": {"score": 66.94, "status": "Fair", "warnings": ["pH level is out of safe range (6.5-8.5)", "Turbidity is high (>5 NTU)"]}}, {"robot_id": "aqua-robot-001", "timestamp": "2025-11-06T05:49:35.459479", "mission": 1, "state": "NAVIGATING", "sensor_readings": {"pH": 7.25, "turbidity": 5.15, "temperature": 23.44, "TDS": 635.46}, "water_quality": {"score": 57.76, "status": "Fair", "warnings": ["Turbidity is high (>5 NTU)", "TDS level is high (>500 ppm)"]}}, {"robot_id": "aqua-robot-001", "timestamp": "2025-11-06T05:49:36.464422", "mission": 1, "state": "NAVIGATING", "sensor_readings": {"pH": 7.65, "turbidity": 4.73, "temperature": 16.04, "TDS": 593.45}, "water_quality": {"score": 57.96, "status": "Fair", "warnings": ["TDS level is high (>500 ppm)"]}}, {"robot_id": "aqua-robot-001", "timestamp": "2025-11-06T05:49:37.469285", "mission": 1, "state": "NAVIGATING", "sensor_readings": {"pH": 8.49, "turbidity": 4.93, "temperature": 23.33, "TDS": 705.04}, "water_quality": {"score": 54.88, "status": "Fair", "warnings": ["TDS level is high (>500 ppm)"]}}, {"robot_id": "aqua-robot-001", "timestamp": "2025-11-06T05:49:38.476578", "mission": 1, "state": "NAVIGATING", "sensor_readings": {"pH": 5.87, "turbidity": 1.02, "temperature": 18.06, "TDS": 588.7}, "water_quality": {"score": 69.34, "status": "Fair", "warnings": ["pH level is out of safe range (6.5-8.5)", "TDS level is high (>500 ppm)"]}}, {"robot_id": "aqua-robot-001", "timestamp": "2025-11-06T05:49:39.484792", "mission": 1, "state": "NAVIGATING", "sensor_readings": {"pH": 7.53, "turbidity": 8.06, "temperature": 26.81, "TDS": 571.65}, "water_quality": {"score": 52.62, "status": "Fair", "warnings": ["Turbidity is high (>5 NTU)", "TDS level is high (>500 ppm)"]}}, {"robot_id": "aqua-robot-001", "timestamp": "2025-11-06T05:57:14.880584", "mission": 1, "state": "NAVIGATING", "sensor_readings": {"pH": 5.66, "turbidity": 3.59, "temperature": 31.04, "TDS": 400.31}, "water_quality": {"score": 55.2, "status": "Fair", "warnings": ["pH level is out of safe range (6.5-8.5)", "Temperature is too high (>30\u00b0C)"]}}, {"robot_id": "aqua-robot-001", "timestamp": "2025-11-06T05:57:15.885797", "mission": 1, "state": "NAVIGATING", "sensor_readings": {"pH": 9.48, "turbidity": 2.74, "temperature": 32.45, "TDS": 972.63}, "water_quality": {"score": 55.24, "status": "Fair", "warnings": ["pH level is out of safe range (6.5-8.5)", "Temperature is too high (>30\u00b0C)", "TDS level is high (>500 ppm)"]}}, {"robot_id": "aqua-robot-001", "timestamp": "2025-11-06T05:57:16.892021", "mission": 1, "state": "NAVIGATING", "sensor_readings": {"pH": 8.01, "turbidity": 3.75, "temperature": 19.49, "TDS": 154.76}, "water_quality": {"score": 76.02, "status": "Good", "warnings": []}}, {"robot_id": "aqua-robot-001", "timestamp": "2025-11-06T05:57:17.897177", "mission": 1, "state": "NAVIGATING", "sensor_readings": {"pH": 6.81, "turbidity": 7.33, "temperature": 16.83, "TDS": 748.67}, "water_quality": {"score": 48.3, "status": "Poor", "warnings": ["Turbidity is high (>5 NTU)", "TDS level is high (>500 ppm)"]}}, {"robot_id": "aqua-robot-001", "timestamp": "2025-11-06T05:57:18.902282", "mission": 1, "state": "NAVIGATING", "sensor_readings": {"pH": 8.22, "turbidity": 3.14, "temperature": 16.13, "TDS": 990.96}, "water_quality": {"score": 63.02, "status": "Fair", "warnings": ["TDS level is high (>500 ppm)"]}}, {"robot_id": "aqua-robot-001", "timestamp": "2025-11-06T05:57:19.907436", "mission": 1, "state": "NAVIGATING", "sensor_readings": {"pH": 6.61, "turbidity": 8.28, "temperature": 16.92, "TDS": 76.39}, "water_quality": {"score": 63.04, "status": "Fair", "warnings": ["Turbidity is high (>5 NTU)"]}}, {"robot_id": "aqua-robot-001", "timestamp": "2025-11-06T05:57:20.912876", "mission": 1, "state": "NAVIGATING", "sensor_readings": {"pH": 9.05, "turbidity": 3.73, "temperature": 28.23, "TDS": 792.73}, "water_quality": {"score": 52.76, "status": "Fair", "warnings": ["pH level is out of safe range (6.5-8.5)", "TDS level is high (>500 ppm)"]}}, {"robot_id": "aqua-robot-001", "timestamp": "2025-11-06T05:57:21.917943", "mission": 1, "state": "NAVIGATING", "sensor_readings": {"pH": 6.75, "turbidity": 2.68, "temperature": 23.24, "TDS": 595.55}, "water_quality": {"score": 67.3, "status": "Fair", "warnings": ["TDS level is high (>500 ppm)"]}}, {"robot_id": "aqua-robot-001", "timestamp": "2025-11-06T05:57:22.925049", "mission": 1, "state": "NAVIGATING", "sensor_readings": {"pH": 7.29, "turbidity": 5.64, "temperature": 25.52, "TDS": 298.18}, "water_quality": {"score": 68.36, "status": "Fair", "warnings": ["Turbidity is high (>5 NTU)"]}}, {"robot_id": "aqua-robot-001", "timestamp": "2025-11-06T05:57:23.931890", "mission": 1, "state": "NAVIGATING", "sensor_readings": {"pH": 8.98, "turbidity": 9.31, "temperature": 30.01, "TDS": 893.88}, "water_quality": {"score": 39.3, "status": "Poor", "warnings": ["pH level is out of safe range (6.5-8.5)", "Turbidity is high (>5 NTU)", "Temperature is too high (>30\u00b0C)", "TDS level is high (>500 ppm)"]}}, {"robot_id": "aqua-robot-001", "timestamp": "2025-11-06T05:57:24.937076", "mission": 1, "state": "NAVIGATING", "sensor_readings": {"pH": 8.07, "turbidity": 6.44, "temperature": 16.32, "TDS": 907.08}, "water_quality": {"score": 50.32, "status": "Fair", "warnings": ["Turbidity is high (>5 NTU)", "TDS level is high (>500 ppm)"]}}, {"robot_id": "aqua-robot-001", "timestamp": "2025-11-06T05:57:25.942492", "mission": 1, "state": "NAVIGATING", "sensor_readings": {"pH": 7.89, "turbidity": 6.3, "temperature": 31.93, "TDS": 389.09}, "water_quality": {"score": 52.7, "status": "Fair", "warnings": ["Turbidity is high (>5 NTU)", "Temperature is too high (>30\u00b0C)"]}}, {"robot_id": "aqua-robot-001", "timestamp": "2025-11-06T05:57:26.947872", "mission": 1, "state": "NAVIGATING", "sensor_readings": {"pH": 8.38, "turbidity": 3.83, "temperature": 16.17, "TDS": 686.05}, "water_quality": {"score": 59.38, "status": "Fair", "warnings": ["TDS level is high (>500 ppm)"]}}, {"robot_id": "aqua-robot-001", "timestamp": "2025-11-06T05:57:27.953230", "mission": 1, "state": "NAVIGATING", "sensor_readings": {"pH": 9.22, "turbidity": 3.09, "temperature": 21.99, "TDS": 425.16}, "water_quality": {"score": 72.08, "status": "Good", "warnings": ["pH level is out of safe range (6.5-8.5)"]}}, {"robot_id": "aqua-robot-001", "timestamp": "2025-11-06T05:57:28.958410", "mission": 1, "state": "NAVIGATING", "sensor_readings": {"pH": 7.38, "turbidity": 7.21, "temperature": 30.32, "TDS": 781.44}, "water_quality": {"score": 39.3, "status": "Poor", "warnings": ["Turbidity is high (>5 NTU)", "Temperature is too high (>30\u00b0C)", "TDS level is high (>500 ppm)"]}}, {"robot_id": "aqua-robot-001", "timestamp": "2025-11-06T05:57:29.963526", "mission": 1, "state": "NAVIGATING", "sensor_readings": {"pH": 8.85, "turbidity": 0.25, "temperature": 25.03, "TDS": 118.21}, "water_quality": {"score": 94.04, "status": "Excellent", "warnings": ["pH level is out of safe range (6.5-8.5)"]}}, {"robot_id": "aqua-robot-001", "timestamp": "2025-11-06T05:57:30.968834", "mission": 1, "state": "NAVIGATING", "sensor_readings": {"pH": 7.06, "turbidity": 6.21, "temperature": 23.62, "TDS": 848.64}, "water_quality": {"score": 49.4, "status": "Poor", "warnings": ["Turbidity is high (>5 NTU)", "TDS level is high (>500 ppm)"]}}, {"robot_id": "aqua-robot-001", "timestamp": "2025-11-06T05:57:31.974260", "mission": 1, "state": "NAVIGATING", "sensor_readings": {"pH": 5.77, "turbidity": 9.63, "temperature": 27.09, "TDS": 292.69}, "water_quality": {"score": 57.46, "status": "Fair", "warnings": ["pH level is out of safe range (6.5-8.5)", "Turbidity is high (>5 NTU)"]}}, {"robot_id": "aqua-robot-001", "timestamp": "2025-11-06T05:57:32.979791", "mission": 1, "state": "NAVIGATING", "sensor_readings": {"pH": 8.98, "turbidity": 2.26, "temperature": 32.32, "TDS": 791.62}, "water_quality": {"score": 57.14, "status": "Fair", "warnings": ["pH level is out of safe range (6.5-8.5)", "Temperature is too high (>30\u00b0C)", "TDS level is high (>500 ppm)"]}}, {"robot_id": "aqua-robot-001", "timestamp": "2025-11-06T05:57:33.985067", "mission": 1, "state": "NAVIGATING", "sensor_readings": {"pH": 9.15, "turbidity": 9.02, "temperature": 24.74, "TDS": 863.6}, "water_quality": {"score": 48.96, "status": "Poor", "warnings": ["pH level is out of safe range (6.5-8.5)", "Turbidity is high (>5 NTU)", "TDS level is high (>500 ppm)"]}}, {"robot_id": "aqua-robot-001", "timestamp": "2025-11-06T05:57:34.990618", "mission": 1, "state": "NAVIGATING", "sensor_readings": {"pH": 9.3, "turbidity": 6.75, "temperature": 21.58, "TDS": 798.69}, "water_quality": {"score": 49.32, "status": "Poor", "warnings": ["pH level is out of safe range (6.5-8.5)", "Turbidity is high (>5 NTU)", "TDS level is high (>500 ppm)"]}}, {"robot_id": "aqua-robot-001", "timestamp": "2025-11-06T05:57:35.996302", "mission": 1, "state": "NAVIGATING", "sensor_readings": {"pH": 5.69, "turbidity": 5.04, "temperature": 16.37, "TDS": 515.04}, "water_quality": {"score": 52.7, "status": "Fair", "warnings": ["pH level is out of safe range (6.5-8.5)", "Turbidity is high (>5 NTU)", "TDS level is high (>500 ppm)"]}}, {"robot_id": "aqua-robot-001", "timestamp": "2025-11-06T05:57:37.001731", "mission": 1, "state": "NAVIGATING", "sensor_readings": {"pH": 7.62, "turbidity": 9.95, "temperature": 34.12, "TDS": 689.39}, "water_quality": {"score": 41.1, "status": "Poor", "warnings": ["Turbidity is high (>5 NTU)", "Temperature is too high (>30\u00b0C)", "TDS level is high (>500 ppm)"]}}, {"robot_id": "aqua-robot-001", "timestamp": "2025-11-06T05:57:38.007172", "mission": 1, "state": "NAVIGATING", "sensor_readings": {"pH": 7.75, "turbidity": 9.15, "temperature": 32.02, "TDS": 398.67}, "water_quality": {"score": 51.1, "status": "Fair", "warnings": ["Turbidity is high (>5 NTU)", "Temperature is too high (>30\u00b0C)"]}}, {"robot_id": "aqua-robot-001", "timestamp": "2025-11-06T05:57:39.013959", "mission": 1, "state": "NAVIGATING", "sensor_readings": {"pH": 8.86, "turbidity": 6.57, "temperature": 29.05, "TDS": 585.85}, "water_quality": {"score": 44.4, "status": "Poor", "warnings": ["pH level is out of safe range (6.5-8.5)", "Turbidity is high (>5 NTU)", "TDS level is high (>500 ppm)"]}}, {"robot_id": "aqua-robot-001", "timestamp": "2025-11-06T05:57:40.021225", "mission": 1, "state": "NAVIGATING", "sensor_readings": {"pH": 7.42, "turbidity": 6.52, "temperature": 16.53, "TDS": 271.55}, "water_quality": {"score": 66.44, "status": "Fair", "warnings": ["Turbidity is high (>5 NTU)"]}}, {"robot_id": "aqua-robot-001", "timestamp": "2025-11-06T05:57:41.027890", "mission": 1, "state": "NAVIGATING", "sensor_readings": {"pH": 7.06, "turbidity": 1.7, "temperature": 25.69, "TDS": 267.28}, "water_quality": {"score": 87.54, "status": "Good", "warnings": []}}, {"robot_id": "aqua-robot-001", "timestamp": "2025-11-06T05:57:42.033570", "mission": 1, "state": "NAVIGATING", "sensor_readings": {"pH": 7.32, "turbidity": 2.17, "temperature": 27.0, "TDS": 368.84}, "water_quality": {"score": 78.34, "status": "Good", "warnings": []}}, {"robot_id": "aqua-robot-001", "timestamp": "2025-11-06T05:57:43.039302", "mission": 1, "state": "NAVIGATING", "sensor_readings": {"pH": 7.92, "turbidity": 7.53, "temperature": 34.51, "TDS": 383.37}, "water_quality": {"score": 49.7, "status": "Poor", "warnings": ["Turbidity is high (>5 NTU)", "Temperature is too high (>30\u00b0C)"]}}, {"robot_id": "aqua-robot-001", "timestamp": "2025-11-06T05:57:44.046251", "mission": 1, "state": "NAVIGATING", "sensor_readings": {"pH": 7.56, "turbidity": 9.28, "temperature": 17.6, "TDS": 112.1}, "water_quality": {"score": 67.34, "status": "Fair", "warnings": ["Turbidity is high (>5 NTU)"]}}, {"robot_id": "aqua-robot-001", "timestamp": "2025-11-06T06:05:54.851108", "mission": 1, "state": "NAVIGATING", "sensor_readings": {"pH": 7.81, "turbidity": 7.76, "temperature": 30.77, "TDS": 425.78}, "water_quality": {"score": 50.28, "status": "Fair", "warnings": ["Turbidity is high (>5 NTU)", "Temperature is too high (>30\u00b0C)"]}}, {"robot_id": "aqua-robot-001", "timestamp": "2025-11-06T06:05:55.857003", "mission": 1, "state": "NAVIGATING", "sensor_readings": {"pH": 8.36, "turbidity": 6.51, "temperature": 22.58, "TDS": 223.95}, "water_quality": {"score": 68.12, "status": "Fair", "warnings": ["Turbidity is high (>5 NTU)"]}}, {"robot_id": "aqua-robot-001", "timestamp": "2025-11-06T06:05:56.862793", "mission": 1, "state": "NAVIGATING", "sensor_readings": {"pH": 6.65, "turbidity": 0.75, "temperature": 16.81, "TDS": 261.13}, "water_quality": {"score": 85.24, "status": "Good", "warnings": []}}, {"robot_id": "aqua-robot-001", "timestamp": "2025-11-06T06:05:57.868427", "mission": 1, "state": "NAVIGATING", "sensor_readings": {"pH": 5.53, "turbidity": 2.01, "temperature": 17.46, "TDS": 787.04}, "water_quality": {"score": 60.28, "status": "Fair", "warnings": ["pH level is out of safe range (6.5-8.5)", "TDS level is high (>500 ppm)"]}}, {"robot_id": "aqua-robot-001", "timestamp": "2025-11-06T06:05:58.874086", "mission": 1, "state": "NAVIGATING", "sensor_readings": {"pH": 8.6, "turbidity": 0.82, "temperature": 31.76, "TDS": 128.66}, "water_quality": {"score": 82.52, "status": "Good", "warnings": ["pH level is out of safe range (6.5-8.5)", "Temperature is too high (>30\u00b0C)"]}}, {"robot_id": "aqua-robot-001", "timestamp": "2025-11-06T06:05:59.879681", "mission": 1, "state": "NAVIGATING", "sensor_readings": {"pH": 8.01, "turbidity": 7.07, "temperature": 22.49, "TDS": 527.24}, "water_quality": {"score": 54.02, "status": "Fair", "warnings": ["Turbidity is high (>5 NTU)", "TDS level is high (>500 ppm)"]}}, {"robot_id": "aqua-robot-001", "timestamp": "2025-11-06T06:06:00.886470", "mission": 1, "state": "NAVIGATING", "sensor_readings": {"pH": 9.32, "turbidity": 7.07, "temperature": 22.08, "TDS": 602.27}, "water_quality": {"score": 53.42, "status": "Fair", "warnings": ["pH level is out of safe range (6.5-8.5)", "Turbidity is high (>5 NTU)", "TDS level is high (>500 ppm)"]}}, {"robot_id": "aqua-robot-001", "timestamp": "2025-11-06T06:06:01.892356", "mission": 1, "state": "NAVIGATING", "sensor_readings": {"pH": 8.02, "turbidity": 3.18, "temperature": 28.41, "TDS": 372.11}, "water_quality": {"score": 70.2, "status": "Good", "warnings": []}}, {"robot_id": "aqua-robot-001", "timestamp": "2025-11-06T06:06:02.898204", "mission": 1, "state": "NAVIGATING", "sensor_readings": {"pH": 7.13, "turbidity": 3.83, "temperature": 22.01, "TDS": 876.08}, "water_quality": {"score": 54.9, "status": "Fair", "warnings": ["TDS level is high (>500 ppm)"]}}, {"robot_id": "aqua-robot-001", "timestamp": "2025-11-06T06:06:03.903987", "mission": 1, "state": "NAVIGATING", "sensor_readings": {"pH": 7.73, "turbidity": 9.48, "temperature": 21.08, "TDS": 986.27}, "water_quality": {"score": 48.96, "status": "Poor", "warnings": ["Turbidity is high (>5 NTU)", "TDS level is high (>500 ppm)"]}}, {"robot_id": "aqua-robot-001", "timestamp": "2025-11-06T06:06:04.909778", "mission": 1, "state": "NAVIGATING", "sensor_readings": {"pH": 6.06, "turbidity": 3.01, "temperature": 31.81, "TDS": 558.74}, "water_quality": {"score": 52.0, "status": "Fair", "warnings": ["pH level is out of safe range (6.5-8.5)", "Temperature is too high (>30\u00b0C)", "TDS level is high (>500 ppm)"]}}, {"robot_id": "aqua-robot-001", "timestamp": "2025-11-06T06:06:05.917262", "mission": 1, "state": "NAVIGATING", "sensor_readings": {"pH": 6.29, "turbidity": 9.14, "temperature": 21.26, "TDS": 279.02}, "water_quality": {"score": 59.84, "status": "Fair", "warnings": ["pH level is out of safe range (6.5-8.5)", "Turbidity is high (>5 NTU)"]}}, {"robot_id": "aqua-robot-001", "timestamp": "2025-11-06T06:06:06.923353", "mission": 1, "state": "NAVIGATING", "sensor_readings": {"pH": 8.25, "turbidity": 2.3, "temperature": 28.43, "TDS": 799.16}, "water_quality": {"score": 60.82, "status": "Fair", "warnings": ["TDS level is high (>500 ppm)"]}}, {"robot_id": "aqua-robot-001", "timestamp": "2025-11-06T06:06:07.931077", "mission": 1, "state": "NAVIGATING", "sensor_readings": {"pH": 6.67, "turbidity": 3.12, "temperature": 31.02, "TDS": 373.88}, "water_quality": {"score": 64.98, "status": "Fair", "warnings": ["Temperature is too high (>30\u00b0C)"]}}, {"robot_id": "aqua-robot-001", "timestamp": "2025-11-06T06:06:08.940288", "mission": 1, "state": "NAVIGATING", "sensor_readings": {"pH": 7.87, "turbidity": 0.52, "temperature": 32.27, "TDS": 559.64}, "water_quality": {"score": 65.9, "status": "Fair", "warnings": ["Temperature is too high (>30\u00b0C)", "TDS level is high (>500 ppm)"]}}, {"robot_id": "aqua-robot-001", "timestamp": "2025-11-06T06:06:09.948454", "mission": 1, "state": "NAVIGATING", "sensor_readings": {"pH": 8.64, "turbidity": 7.53, "temperature": 27.09, "TDS": 163.54}, "water_quality": {"score": 65.84, "status": "Fair", "warnings": ["pH level is out of safe range (6.5-8.5)", "Turbidity is high (>5 NTU)"]}}, {"robot_id": "aqua-robot-001", "timestamp": "2025-11-06T06:06:10.955988", "mission": 1, "state": "NAVIGATING", "sensor_readings": {"pH": 9.26, "turbidity": 1.62, "temperature": 18.58, "TDS": 122.24}, "water_quality": {"score": 92.78, "status": "Excellent", "warnings": ["pH level is out of safe range (6.5-8.5)"]}}, {"robot_id": "aqua-robot-001", "timestamp": "2025-11-06T06:06:11.962277", "mission": 1, "state": "NAVIGATING", "sensor_readings": {"pH": 6.18, "turbidity": 5.34, "temperature": 32.75, "TDS": 71.59}, "water_quality": {"score": 55.2, "status": "Fair", "warnings": ["pH level is out of safe range (6.5-8.5)", "Turbidity is high (>5 NTU)", "Temperature is too high (>30\u00b0C)"]}}, {"robot_id": "aqua-robot-001", "timestamp": "2025-11-06T06:06:12.968517", "mission": 1, "state": "NAVIGATING", "sensor_readings": {"pH": 8.08, "turbidity": 2.42, "temperature": 30.71, "TDS": 210.4}, "water_quality": {"score": 77.42, "status": "Good", "warnings": ["Temperature is too high (>30\u00b0C)"]}}, {"robot_id": "aqua-robot-001", "timestamp": "2025-11-06T06:06:13.974604", "mission": 1, "state": "NAVIGATING", "sensor_readings": {"pH": 8.71, "turbidity": 2.8, "temperature": 23.58, "TDS": 322.9}, "water_quality": {"score": 78.22, "status": "Good", "warnings": ["pH level is out of safe range (6.5-8.5)"]}}, {"robot_id": "aqua-robot-001", "timestamp": "2025-11-06T06:06:14.980619", "mission": 1, "state": "NAVIGATING", "sensor_readings": {"pH": 5.89, "turbidity": 3.38, "temperature": 21.45, "TDS": 193.26}, "water_quality": {"score": 75.7, "status": "Good", "warnings": ["pH level is out of safe range (6.5-8.5)"]}}, {"robot_id": "aqua-robot-001", "timestamp": "2025-11-06T06:06:15.988529", "mission": 1, "state": "NAVIGATING", "sensor_readings": {"pH": 6.09, "turbidity": 8.76, "temperature": 19.49, "TDS": 957.31}, "water_quality": {"score": 43.7, "status": "Poor", "warnings": ["pH level is out of safe range (6.5-8.5)", "Turbidity is high (>5 NTU)", "TDS level is high (>500 ppm)"]}}, {"robot_id": "aqua-robot-001", "timestamp": "2025-11-06T06:06:16.994948", "mission": 1, "state": "NAVIGATING", "sensor_readings": {"pH": 5.92, "turbidity": 2.6, "temperature": 15.91, "TDS": 314.64}, "water_quality": {"score": 76.58, "status": "Good", "warnings": ["pH level is out of safe range (6.5-8.5)"]}}, {"robot_id": "aqua-robot-001", "timestamp": "2025-11-06T06:06:18.001360", "mission": 1, "state": "NAVIGATING", "sensor_readings": {"pH": 8.76, "turbidity": 7.32, "temperature": 19.91, "TDS": 240.15}, "water_quality": {"score": 68.0, "status": "Fair", "warnings": ["pH level is out of safe range (6.5-8.5)", "Turbidity is high (>5 NTU)"]}}, {"robot_id": "aqua-robot-001", "timestamp": "2025-11-06T06:06:19.007567", "mission": 1, "state": "NAVIGATING", "sensor_readings": {"pH": 6.73, "turbidity": 0.28, "temperature": 34.56, "TDS": 611.62}, "water_quality": {"score": 60.88, "status": "Fair", "warnings": ["Temperature is too high (>30\u00b0C)", "TDS level is high (>500 ppm)"]}}, {"robot_id": "aqua-robot-001", "timestamp": "2025-11-06T06:06:20.013886", "mission": 1, "state": "NAVIGATING", "sensor_readings": {"pH": 8.11, "turbidity": 6.33, "temperature": 24.32, "TDS": 495.13}, "water_quality": {"score": 54.86, "status": "Fair", "warnings": ["Turbidity is high (>5 NTU)"]}}, {"robot_id": "aqua-robot-001", "timestamp": "2025-11-06T06:06:21.022092", "mission": 1, "state": "NAVIGATING", "sensor_readings": {"pH": 6.05, "turbidity": 4.72, "temperature": 23.25, "TDS": 578.29}, "water_quality": {"score": 52.5, "status": "Fair", "warnings": ["pH level is out of safe range (6.5-8.5)", "TDS level is high (>500 ppm)"]}}, {"robot_id": "aqua-robot-001", "timestamp": "2025-11-06T06:06:22.028397", "mission": 1, "state": "NAVIGATING", "sensor_readings": {"pH": 8.35, "turbidity": 5.79, "temperature": 33.37, "TDS": 548.82}, "water_quality": {"score": 46.2, "status": "Poor", "warnings": ["Turbidity is high (>5 NTU)", "Temperature is too high (>30\u00b0C)", "TDS level is high (>500 ppm)"]}}, {"robot_id": "aqua-robot-001", "timestamp": "2025-11-06T06:06:23.034544", "mission": 1, "state": "NAVIGATING", "sensor_readings": {"pH": 5.74, "turbidity": 7.13, "temperature": 28.92, "TDS": 297.22}, "water_quality": {"score": 51.62, "status": "Fair", "warnings": ["pH level is out of safe range (6.5-8.5)", "Turbidity is high (>5 NTU)"]}}, {"robot_id": "aqua-robot-001", "timestamp": "2025-11-06T06:06:24.040878", "mission": 1, "state": "NAVIGATING", "sensor_readings": {"pH": 6.37, "turbidity": 8.53, "temperature": 16.77, "TDS": 583.65}, "water_quality": {"score": 48.4, "status": "Poor", "warnings": ["pH level is out of safe range (6.5-8.5)", "Turbidity is high (>5 NTU)", "TDS level is high (>500 ppm)"]}}, {"robot_id": "aqua-robot-001", "timestamp": "2025-11-06T06:10:43.914004", "mission": 1, "state": "NAVIGATING", "sensor_readings": {"pH": 5.72, "turbidity": 2.55, "temperature": 31.36, "TDS": 414.09}, "water_quality": {"score": 61.6, "status": "Fair", "warnings": ["pH level is out of safe range (6.5-8.5)", "Temperature is too high (>30\u00b0C)"]}}, {"robot_id": "aqua-robot-001", "timestamp": "2025-11-06T06:10:44.920754", "mission": 1, "state": "NAVIGATING", "sensor_readings": {"pH": 6.01, "turbidity": 5.56, "temperature": 25.12, "TDS": 684.88}, "water_quality": {"score": 50.9, "status": "Fair", "warnings": ["pH level is out of safe range (6.5-8.5)", "Turbidity is high (>5 NTU)", "TDS level is high (>500 ppm)"]}}, {"robot_id": "aqua-robot-001", "timestamp": "2025-11-06T06:10:45.927031", "mission": 1, "state": "NAVIGATING", "sensor_readings": {"pH": 7.05, "turbidity": 9.84, "temperature": 17.1, "TDS": 594.76}, "water_quality": {"score": 52.3, "status": "Fair", "warnings": ["Turbidity is high (>5 NTU)", "TDS level is high (>500 ppm)"]}}, {"robot_id": "aqua-robot-001", "timestamp": "2025-11-06T06:10:46.933258", "mission": 1, "state": "NAVIGATING", "sensor_readings": {"pH": 8.92, "turbidity": 5.32, "temperature": 32.26, "TDS": 780.55}, "water_quality": {"score": 44.66, "status": "Poor", "warnings": ["pH level is out of safe range (6.5-8.5)", "Turbidity is high (>5 NTU)", "Temperature is too high (>30\u00b0C)", "TDS level is high (>500 ppm)"]}}, {"robot_id": "aqua-robot-001", "timestamp": "2025-11-06T06:10:47.939582", "mission": 1, "state": "NAVIGATING", "sensor_readings": {"pH": 8.52, "turbidity": 0.82, "temperature": 22.38, "TDS": 581.32}, "water_quality": {"score": 78.04, "status": "Good", "warnings": ["pH level is out of safe range (6.5-8.5)", "TDS level is high (>500 ppm)"]}}, {"robot_id": "aqua-robot-001", "timestamp": "2025-11-06T06:10:48.946085", "mission": 1, "state": "NAVIGATING", "sensor_readings": {"pH": 5.66, "turbidity": 8.48, "temperature": 25.85, "TDS": 883.53}, "water_quality": {"score": 42.8, "status": "Poor", "warnings": ["pH level is out of safe range (6.5-8.5)", "Turbidity is high (>5 NTU)", "TDS level is high (>500 ppm)"]}}, {"robot_id": "aqua-robot-001", "timestamp": "2025-11-06T06:10:49.952447", "mission": 1, "state": "NAVIGATING", "sensor_readings": {"pH": 7.99, "turbidity": 4.29, "temperature": 24.8, "TDS": 729.59}, "water_quality": {"score": 53.9, "status": "Fair", "warnings": ["TDS level is high (>500 ppm)"]}}, {"robot_id": "aqua-robot-001", "timestamp": "2025-11-06T06:10:50.958947", "mission": 1, "state": "NAVIGATING", "sensor_readings": {"pH": 6.93, "turbidity": 6.53, "temperature": 22.98, "TDS": 143.04}, "water_quality": {"score": 67.4, "status": "Fair", "warnings": ["Turbidity is high (>5 NTU)"]}}, {"robot_id": "aqua-robot-001", "timestamp": "2025-11-06T06:10:51.965474", "mission": 1, "state": "NAVIGATING", "sensor_readings": {"pH": 6.11, "turbidity": 5.87, "temperature": 26.74, "TDS": 811.36}, "water_quality": {"score": 45.24, "status": "Poor", "warnings": ["pH level is out of safe range (6.5-8.5)", "Turbidity is high (>5 NTU)", "TDS level is high (>500 ppm)"]}}, {"robot_id": "aqua-robot-001", "timestamp": "2025-11-06T06:10:52.973948", "mission": 1, "state": "NAVIGATING", "sensor_readings": {"pH": 9.06, "turbidity": 7.45, "temperature": 23.93, "TDS": 709.03}, "water_quality": {"score": 48.96, "status": "Poor", "warnings": ["pH level is out of safe range (6.5-8.5)", "Turbidity is high (>5 NTU)", "TDS level is high (>500 ppm)"]}}, {"robot_id": "aqua-robot-001", "timestamp": "2025-11-06T06:10:53.982192", "mission": 1, "state": "NAVIGATING", "sensor_readings": {"pH": 7.5, "turbidity": 2.45, "temperature": 34.38, "TDS": 300.98}, "water_quality": {"score": 72.54, "status": "Good", "warnings": ["Temperature is too high (>30\u00b0C)"]}}, {"robot_id": "aqua-robot-001", "timestamp": "2025-11-06T06:10:54.988809", "mission": 1, "state": "NAVIGATING", "sensor_readings": {"pH": 7.14, "turbidity": 9.86, "temperature": 26.23, "TDS": 882.71}, "water_quality": {"score": 47.62, "status": "Poor", "warnings": ["Turbidity is high (>5 NTU)", "TDS level is high (>500 ppm)"]}}, {"robot_id": "aqua-robot-001", "timestamp": "2025-11-06T06:10:55.995341", "mission": 1, "state": "NAVIGATING", "sensor_readings": {"pH": 8.67, "turbidity": 3.5, "temperature": 28.0, "TDS": 470.91}, "water_quality": {"score": 61.64, "status": "Fair", "warnings": ["pH level is out of safe range (6.5-8.5)"]}}, {"robot_id": "aqua-robot-001", "timestamp": "2025-11-06T06:10:57.002316", "mission": 1, "state": "NAVIGATING", "sensor_readings": {"pH": 6.03, "turbidity": 8.23, "temperature": 28.69, "TDS": 217.1}, "water_quality": {"score": 53.8, "status": "Fair", "warnings": ["pH level is out of safe range (6.5-8.5)", "Turbidity is high (>5 NTU)"]}}, {"robot_id": "aqua-robot-001", "timestamp": "2025-11-06T06:10:58.008914", "mission": 1, "state": "NAVIGATING", "sensor_readings": {"pH": 6.48, "turbidity": 9.94, "temperature": 28.19, "TDS": 148.33}, "water_quality": {"score": 56.06, "status": "Fair", "warnings": ["pH level is out of safe range (6.5-8.5)", "Turbidity is high (>5 NTU)"]}}, {"robot_id": "aqua-robot-001", "timestamp": "2025-11-06T06:10:59.015473", "mission": 1, "state": "NAVIGATING", "sensor_readings": {"pH": 5.88, "turbidity": 9.15, "temperature": 23.02, "TDS": 882.68}, "water_quality": {"score": 43.3, "status": "Poor", "warnings": ["pH level is out of safe range (6.5-8.5)", "Turbidity is high (>5 NTU)", "TDS level is high (>500 ppm)"]}}, {"robot_id": "aqua-robot-001", "timestamp": "2025-11-06T06:11:00.022196", "mission": 1, "state": "NAVIGATING", "sensor_readings": {"pH": 6.59, "turbidity": 5.2, "temperature": 17.58, "TDS": 285.97}, "water_quality": {"score": 65.14, "status": "Fair", "warnings": ["Turbidity is high (>5 NTU)"]}}, {"robot_id": "aqua-robot-001", "timestamp": "2025-11-06T06:11:01.029023", "mission": 1, "state": "NAVIGATING", "sensor_readings": {"pH": 6.4, "turbidity": 4.23, "temperature": 23.41, "TDS": 459.59}, "water_quality": {"score": 59.0, "status": "Fair", "warnings": ["pH level is out of safe range (6.5-8.5)"]}}, {"robot_id": "aqua-robot-001", "timestamp": "2025-11-06T06:11:02.036055", "mission": 1, "state": "NAVIGATING", "sensor_readings": {"pH": 7.24, "turbidity": 9.77, "temperature": 29.63, "TDS": 798.29}, "water_quality": {"score": 38.7, "status": "Poor", "warnings": ["Turbidity is high (>5 NTU)", "TDS level is high (>500 ppm)"]}}, {"robot_id": "aqua-robot-001", "timestamp": "2025-11-06T06:11:03.042847", "mission": 1, "state": "NAVIGATING", "sensor_readings": {"pH": 7.07, "turbidity": 9.96, "temperature": 20.92, "TDS": 696.37}, "water_quality": {"score": 50.8, "status": "Fair", "warnings": ["Turbidity is high (>5 NTU)", "TDS level is high (>500 ppm)"]}}, {"robot_id": "aqua-robot-001", "timestamp": "2025-11-06T06:11:04.049646", "mission": 1, "state": "NAVIGATING", "sensor_readings": {"pH": 6.9, "turbidity": 6.08, "temperature": 24.21, "TDS": 198.25}, "water_quality": {"score": 67.38, "status": "Fair", "warnings": ["Turbidity is high (>5 NTU)"]}}, {"robot_id": "aqua-robot-001", "timestamp": "2025-11-06T06:11:05.056257", "mission": 1, "state": "NAVIGATING", "sensor_readings": {"pH": 8.01, "turbidity": 9.58, "temperature": 32.21, "TDS": 387.53}, "water_quality": {"score": 51.42, "status": "Fair", "warnings": ["Turbidity is high (>5 NTU)", "Temperature is too high (>30\u00b0C)"]}}, {"robot_id": "aqua-robot-001", "timestamp": "2025-11-06T06:11:06.063143", "mission": 1, "state": "NAVIGATING", "sensor_readings": {"pH": 6.6, "turbidity": 9.57, "temperature": 34.95, "TDS": 109.12}, "water_quality": {"score": 49.5, "status": "Poor", "warnings": ["Turbidity is high (>5 NTU)", "Temperature is too high (>30\u00b0C)"]}}, {"robot_id": "aqua-robot-001", "timestamp": "2025-11-06T06:11:07.070057", "mission": 1, "state": "NAVIGATING", "sensor_readings": {"pH": 6.67, "turbidity": 9.2, "temperature": 27.05, "TDS": 755.83}, "water_quality": {"score": 43.64, "status": "Poor", "warnings": ["Turbidity is high (>5 NTU)", "TDS level is high (>500 ppm)"]}}, {"robot_id": "aqua-robot-001", "timestamp": "2025-11-06T06:11:08.077009", "mission": 1, "state": "NAVIGATING", "sensor_readings": {"pH": 8.81, "turbidity": 5.34, "temperature": 29.9, "TDS": 55.83}, "water_quality": {"score": 63.74, "status": "Fair", "warnings": ["pH level is out of safe range (6.5-8.5)", "Turbidity is high (>5 NTU)"]}}, {"robot_id": "aqua-robot-001", "timestamp": "2025-11-06T06:11:09.084114", "mission": 1, "state": "NAVIGATING", "sensor_readings": {"pH": 8.24, "turbidity": 9.68, "temperature": 19.87, "TDS": 674.79}, "water_quality": {"score": 51.92, "status": "Fair", "warnings": ["Turbidity is high (>5 NTU)", "TDS level is high (>500 ppm)"]}}, {"robot_id": "aqua-robot-001", "timestamp": "2025-11-06T06:11:10.091053", "mission": 1, "state": "NAVIGATING", "sensor_readings": {"pH": 6.16, "turbidity": 2.54, "temperature": 33.19, "TDS": 489.22}, "water_quality": {"score": 53.1, "status": "Fair", "warnings": ["pH level is out of safe range (6.5-8.5)", "Temperature is too high (>30\u00b0C)"]}}, {"robot_id": "aqua-robot-001", "timestamp": "2025-11-06T06:11:11.098258", "mission": 1, "state": "NAVIGATING", "sensor_readings": {"pH": 6.62, "turbidity": 1.01, "temperature": 23.3, "TDS": 67.68}, "water_quality": {"score": 86.38, "status": "Good", "warnings": []}}, {"robot_id": "aqua-robot-001", "timestamp": "2025-11-06T06:11:12.107811", "mission": 1, "state": "NAVIGATING", "sensor_readings": {"pH": 5.68, "turbidity": 1.66, "temperature": 15.5, "TDS": 568.92}, "water_quality": {"score": 69.08, "status": "Fair", "warnings": ["pH level is out of safe range (6.5-8.5)", "TDS level is high (>500 ppm)"]}}, {"robot_id": "aqua-robot-001", "timestamp": "2025-11-06T06:11:13.118601", "mission": 1, "state": "NAVIGATING", "sensor_readings": {"pH": 7.14, "turbidity": 2.48, "temperature": 26.89, "TDS": 490.6}, "water_quality": {"score": 70.22, "status": "Good", "warnings": []}}, {"robot_id": "aqua-robot-001", "timestamp": "2025-11-06T06:11:36.994730", "mission": 1, "state": "NAVIGATING", "sensor_readings": {"pH": 6.98, "turbidity": 5.87, "temperature": 23.36, "TDS": 218.58}, "water_quality": {"score": 68.84, "status": "Fair", "warnings": ["Turbidity is high (>5 NTU)"]}}, {"robot_id": "aqua-robot-001", "timestamp": "2025-11-06T06:11:38.006196", "mission": 1, "state": "NAVIGATING", "sensor_readings": {"pH": 7.14, "turbidity": 5.36, "temperature": 34.34, "TDS": 473.28}, "water_quality": {"score": 51.0, "status": "Fair", "warnings": ["Turbidity is high (>5 NTU)", "Temperature is too high (>30\u00b0C)"]}}, {"robot_id": "aqua-robot-001", "timestamp": "2025-11-06T06:11:39.013384", "mission": 1, "state": "NAVIGATING", "sensor_readings": {"pH": 6.79, "turbidity": 5.01, "temperature": 19.82, "TDS": 620.68}, "water_quality": {"score": 56.7, "status": "Fair", "warnings": ["Turbidity is high (>5 NTU)", "TDS level is high (>500 ppm)"]}}, {"robot_id": "aqua-robot-001", "timestamp": "2025-11-06T06:11:40.021749", "mission": 1, "state": "NAVIGATING", "sensor_readings": {"pH": 6.67, "turbidity": 5.86, "temperature": 24.35, "TDS": 812.31}, "water_quality": {"score": 47.5, "status": "Poor", "warnings": ["Turbidity is high (>5 NTU)", "TDS level is high (>500 ppm)"]}}, {"robot_id": "aqua-robot-001", "timestamp": "2025-11-06T06:11:41.030922", "mission": 1, "state": "NAVIGATING", "sensor_readings": {"pH": 7.28, "turbidity": 5.48, "temperature": 33.18, "TDS": 668.84}, "water_quality": {"score": 46.4, "status": "Poor", "warnings": ["Turbidity is high (>5 NTU)", "Temperature is too high (>30\u00b0C)", "TDS level is high (>500 ppm)"]}}, {"robot_id": "aqua-robot-001", "timestamp": "2025-11-06T06:11:42.038294", "mission": 1, "state": "NAVIGATING", "sensor_readings": {"pH": 9.49, "turbidity": 0.14, "temperature": 24.38, "TDS": 410.9}, "water_quality": {"score": 83.74, "status": "Good", "warnings": ["pH level is out of safe range (6.5-8.5)"]}}, {"robot_id": "aqua-robot-001", "timestamp": "2025-11-06T06:11:43.045560", "mission": 1, "state": "NAVIGATING", "sensor_readings": {"pH": 8.13, "turbidity": 3.43, "temperature": 28.73, "TDS": 483.06}, "water_quality": {"score": 58.9, "status": "Fair", "warnings": []}}, {"robot_id": "aqua-robot-001", "timestamp": "2025-11-06T06:11:44.052772", "mission": 1, "state": "NAVIGATING", "sensor_readings": {"pH": 9.02, "turbidity": 4.35, "temperature": 29.47, "TDS": 345.96}, "water_quality": {"score": 61.94, "status": "Fair", "warnings": ["pH level is out of safe range (6.5-8.5)"]}}, {"robot_id": "aqua-robot-001", "timestamp": "2025-11-06T06:11:45.059947", "mission": 1, "state": "NAVIGATING", "sensor_readings": {"pH": 7.65, "turbidity": 1.18, "temperature": 24.21, "TDS": 339.49}, "water_quality": {"score": 87.48, "status": "Good", "warnings": []}}, {"robot_id": "aqua-robot-001", "timestamp": "2025-11-06T06:11:46.067232", "mission": 1, "state": "NAVIGATING", "sensor_readings": {"pH": 8.6, "turbidity": 9.95, "temperature": 18.77, "TDS": 974.33}, "water_quality": {"score": 49.32, "status": "Poor", "warnings": ["pH level is out of safe range (6.5-8.5)", "Turbidity is high (>5 NTU)", "TDS level is high (>500 ppm)"]}}, {"robot_id": "aqua-robot-001", "timestamp": "2025-11-06T06:11:47.074463", "mission": 1, "state": "NAVIGATING", "sensor_readings": {"pH": 7.37, "turbidity": 9.78, "temperature": 34.02, "TDS": 572.23}, "water_quality": {"score": 42.6, "status": "Poor", "warnings": ["Turbidity is high (>5 NTU)", "Temperature is too high (>30\u00b0C)", "TDS level is high (>500 ppm)"]}}, {"robot_id": "aqua-robot-001", "timestamp": "2025-11-06T06:11:48.081696", "mission": 1, "state": "NAVIGATING", "sensor_readings": {"pH": 8.06, "turbidity": 5.97, "temperature": 27.29, "TDS": 922.45}, "water_quality": {"score": 49.44, "status": "Poor", "warnings": ["Turbidity is high (>5 NTU)", "TDS level is high (>500 ppm)"]}}, {"robot_id": "aqua-robot-001", "timestamp": "2025-11-06T06:11:49.088892", "mission": 1, "state": "NAVIGATING", "sensor_readings": {"pH": 6.63, "turbidity": 3.37, "temperature": 30.31, "TDS": 181.56}, "water_quality": {"score": 66.1, "status": "Fair", "warnings": ["Temperature is too high (>30\u00b0C)"]}}, {"robot_id": "aqua-robot-001", "timestamp": "2025-11-06T06:11:50.096907", "mission": 1, "state": "NAVIGATING", "sensor_readings": {"pH": 8.02, "turbidity": 9.02, "temperature": 23.44, "TDS": 236.29}, "water_quality": {"score": 67.64, "status": "Fair", "warnings": ["Turbidity is high (>5 NTU)"]}}, {"robot_id": "aqua-robot-001", "timestamp": "2025-11-06T06:11:51.104325", "mission": 1, "state": "NAVIGATING", "sensor_readings": {"pH": 8.48, "turbidity": 6.68, "temperature": 24.12, "TDS": 831.06}, "water_quality": {"score": 48.96, "status": "Poor", "warnings": ["Turbidity is high (>5 NTU)", "TDS level is high (>500 ppm)"]}}, {"robot_id": "aqua-robot-001", "timestamp": "2025-11-06T06:11:52.111762", "mission": 1, "state": "NAVIGATING", "sensor_readings": {"pH": 5.54, "turbidity": 4.65, "temperature": 31.39, "TDS": 965.22}, "water_quality": {"score": 38.6, "status": "Poor", "warnings": ["pH level is out of safe range (6.5-8.5)", "Temperature is too high (>30\u00b0C)", "TDS level is high (>500 ppm)"]}}, {"robot_id": "aqua-robot-001", "timestamp": "2025-11-06T06:11:53.119258", "mission": 1, "state": "NAVIGATING", "sensor_readings": {"pH": 7.17, "turbidity": 1.56, "temperature": 32.02, "TDS": 263.86}, "water_quality": {"score": 77.4, "status": "Good", "warnings": ["Temperature is too high (>30\u00b0C)"]}}, {"robot_id": "aqua-robot-001", "timestamp": "2025-11-06T06:11:54.126723", "mission": 1, "state": "NAVIGATING", "sensor_readings": {"pH": 6.77, "turbidity": 6.94, "temperature": 34.7, "TDS": 869.48}, "water_quality": {"score": 37.1, "status": "Poor", "warnings": ["Turbidity is high (>5 NTU)", "Temperature is too high (>30\u00b0C)", "TDS level is high (>500 ppm)"]}}, {"robot_id": "aqua-robot-001", "timestamp": "2025-11-06T06:11:55.134105", "mission": 1, "state": "NAVIGATING", "sensor_readings": {"pH": 6.53, "turbidity": 8.16, "temperature": 20.86, "TDS": 857.94}, "water_quality": {"score": 44.3, "status": "Poor", "warnings": ["Turbidity is high (>5 NTU)", "TDS level is high (>500 ppm)"]}}, {"robot_id": "aqua-robot-001", "timestamp": "2025-11-06T06:11:56.141669", "mission": 1, "state": "NAVIGATING", "sensor_readings": {"pH": 8.8, "turbidity": 2.05, "temperature": 19.01, "TDS": 738.08}, "water_quality": {"score": 68.04, "status": "Fair", "warnings": ["pH level is out of safe range (6.5-8.5)", "TDS level is high (>500 ppm)"]}}, {"robot_id": "aqua-robot-001", "timestamp": "2025-11-06T06:11:57.149299", "mission": 1, "state": "NAVIGATING", "sensor_readings": {"pH": 6.49, "turbidity": 6.79, "temperature": 21.74, "TDS": 725.39}, "water_quality": {"score": 44.3, "status": "Poor", "warnings": ["pH level is out of safe range (6.5-8.5)", "Turbidity is high (>5 NTU)", "TDS level is high (>500 ppm)"]}}, {"robot_id": "aqua-robot-001", "timestamp": "2025-11-06T06:11:58.157082", "mission": 1, "state": "NAVIGATING", "sensor_readings": {"pH": 9.0, "turbidity": 8.33, "temperature": 23.73, "TDS": 956.6}, "water_quality": {"score": 48.96, "status": "Poor", "warnings": ["pH level is out of safe range (6.5-8.5)", "Turbidity is high (>5 NTU)", "TDS level is high (>500 ppm)"]}}, {"robot_id": "aqua-robot-001", "timestamp": "2025-11-06T06:11:59.165363", "mission": 1, "state": "NAVIGATING", "sensor_readings": {"pH": 9.03, "turbidity": 2.74, "temperature": 29.97, "TDS": 221.26}, "water_quality": {"score": 75.26, "status": "Good", "warnings": ["pH level is out of safe range (6.5-8.5)"]}}, {"robot_id": "aqua-robot-001", "timestamp": "2025-11-06T06:12:00.172859", "mission": 1, "state": "NAVIGATING", "sensor_readings": {"pH": 7.93, "turbidity": 0.57, "temperature": 19.62, "TDS": 419.61}, "water_quality": {"score": 83.48, "status": "Good", "warnings": []}}, {"robot_id": "aqua-robot-001", "timestamp": "2025-11-06T06:12:01.180403", "mission": 1, "state": "NAVIGATING", "sensor_readings": {"pH": 8.81, "turbidity": 5.37, "temperature": 21.1, "TDS": 570.35}, "water_quality": {"score": 58.98, "status": "Fair", "warnings": ["pH level is out of safe range (6.5-8.5)", "Turbidity is high (>5 NTU)", "TDS level is high (>500 ppm)"]}}, {"robot_id": "aqua-robot-001", "timestamp": "2025-11-06T06:12:02.187984", "mission": 1, "state": "NAVIGATING", "sensor_readings": {"pH": 8.02, "turbidity": 1.11, "temperature": 25.22, "TDS": 275.22}, "water_quality": {"score": 90.48, "status": "Excellent", "warnings": []}}, {"robot_id": "aqua-robot-001", "timestamp": "2025-11-06T06:12:03.195640", "mission": 1, "state": "NAVIGATING", "sensor_readings": {"pH": 8.94, "turbidity": 7.4, "temperature": 31.01, "TDS": 631.55}, "water_quality": {"score": 43.5, "status": "Poor", "warnings": ["pH level is out of safe range (6.5-8.5)", "Turbidity is high (>5 NTU)", "Temperature is too high (>30\u00b0C)", "TDS level is high (>500 ppm)"]}}, {"robot_id": "aqua-robot-001", "timestamp": "2025-11-06T06:12:04.203325", "mission": 1, "state": "NAVIGATING", "sensor_readings": {"pH": 6.09, "turbidity": 4.32, "temperature": 16.74, "TDS": 359.19}, "water_quality": {"score": 64.2, "status": "Fair", "warnings": ["pH level is out of safe range (6.5-8.5)"]}}, {"robot_id": "aqua-robot-001", "timestamp": "2025-11-06T06:12:05.211085", "mission": 1, "state": "NAVIGATING", "sensor_readings": {"pH": 7.78, "turbidity": 0.9, "temperature": 32.94, "TDS": 136.53}, "water_quality": {"score": 80.2, "status": "Good", "warnings": ["Temperature is too high (>30\u00b0C)"]}}, {"robot_id": "aqua-robot-001", "timestamp": "2025-11-06T06:12:06.218654", "mission": 1, "state": "NAVIGATING", "sensor_readings": {"pH": 6.45, "turbidity": 7.6, "temperature": 20.31, "TDS": 791.06}, "water_quality": {"score": 44.3, "status": "Poor", "warnings": ["pH level is out of safe range (6.5-8.5)", "Turbidity is high (>5 NTU)", "TDS level is high (>500 ppm)"]}}]